{"chunk_definitions":[{"row":24,"row_count":1,"visible":true,"expansion_state":0,"options":{"engine":"r","label":"Setup","include":false,"results":"hide","warning":false},"document_id":"4665E884","chunk_id":"csetup_chunk","chunk_label":"Setup"},{"row":37,"row_count":1,"visible":true,"expansion_state":0,"options":{"engine":"r","label":"unnamed-chunk-1"},"document_id":"4665E884","chunk_id":"cnt3ptvsp5fb8","chunk_label":"unnamed-chunk-1"},{"row":46,"row_count":1,"visible":true,"expansion_state":0,"options":{"engine":"r","label":"unnamed-chunk-30"},"document_id":"4665E884","chunk_id":"cck1xmbp8l361","chunk_label":"unnamed-chunk-2"},{"row":60,"row_count":1,"visible":true,"expansion_state":0,"options":{"engine":"r","label":"unnamed-chunk-27"},"document_id":"4665E884","chunk_id":"cvu1r7vltrjbj","chunk_label":"unnamed-chunk-3"}],"doc_write_time":1648770609}